{"inkVersion":20,"root":[["^Title_Continue : galmuri11_36_0_0_0","\n","^Title_NewGame : galmuri11_36_0_0_0","\n","^Title_Options : galmuri11_36_0_0_0","\n","^Title_Quit : galmuri11_36_0_0_0","\n","^Title_Prompt : galmuri11_36_0_0_0","\n","^Title_Prompt_Yes : galmuri11_24_0_0_0","\n","^Title_Prompt_No : galmuri11_24_0_0_0","\n","^LoadingText : galmuri11_36_5_0_0","\n","^BindingResetPrompt_Main : galmuri11_36_0_0_0","\n","^BindingResetPrompt_Yes : galmuri11_36_0_0_0","\n","^BindingResetPrompt_No : galmuri11_36_0_0_0","\n","^ConfirmPrompt : galmuri11_36_0_0_0","\n","^ConfirmPrompt_Yes : galmuri11_36_0_0_0","\n","^ConfirmPrompt_No : galmuri11_36_0_0_0","\n","^ReviveCost_Text : galmuri11_18_0_0_0","\n","^BattleLost_MoneyMessage : galmuri11_14_0_0_0","\n","^Resultcard_Counter_Text : galmuri11_16_0_0_0","\n","^Resultcard_Parry_Text : galmuri11_16_0_0_0","\n","^Resultcard_Super_Text : galmuri11_16_0_0_0","\n","^BattleWon_ExpMessage : galmuri11_12_0_0_0","\n","^Dialogue_TextField : galmuri11_36_0_0_64.27","\n","^Choicebox_Yes : galmuri11_36_0_0_0","\n","^Choicebox_No : galmuri11_36_0_0_0","\n","^Paused : galmuri11_48_0_0_0","\n","^Back : galmuri11_36_0_0_0","\n","^Save : galmuri11_36_0_0_0","\n","^Load : galmuri11_36_0_0_0","\n","^Options : galmuri11_36_0_0_0","\n","^Quit : galmuri11_36_0_0_0","\n","^Menu_Graphic_Text : galmuri11_36_0_0_0","\n","^Menu_Controls_Text : galmuri11_36_0_0_0","\n","^Menu_Sound_Text : galmuri11_36_0_0_0","\n","^Graphic_Resolution : galmuri11_48_0_0_0","\n","^Graphic_Fullscreen : galmuri11_19_0_0_0","\n","^Controls_Freeroam : galmuri11_40_0_0_0","\n","^Controls_Battle : galmuri11_40_0_0_0","\n","^Controls_Roam_0 : galmuri11_36_0_0_0","\n","^Controls_Roam_1 : galmuri11_36_0_0_0","\n","^Controls_Roam_2 : galmuri11_36_0_0_0","\n","^Controls_Roam_3 : galmuri11_36_0_0_0","\n","^Controls_Roam_4 : galmuri11_36_0_0_0","\n","^Controls_Roam_5 : galmuri11_36_0_0_0","\n","^Controls_Roam_6 : galmuri11_36_0_0_0","\n","^Controls_Roam_7 : galmuri11_36_0_0_0","\n","^Controls_Roam_8 : galmuri11_36_0_0_0","\n","^Controls_Battle_0 : galmuri11_36_0_0_0","\n","^Controls_Battle_1 : galmuri11_36_0_0_0","\n","^Controls_Battle_2 : galmuri11_36_0_0_0","\n","^Controls_Battle_3 : galmuri11_36_0_0_0","\n","^Controls_Battle_4 : galmuri11_36_0_0_0","\n","^Controls_Battle_5 : galmuri11_36_0_0_0","\n","^Controls_Battle_6 : galmuri11_36_0_0_0","\n","^Controls_Battle_7 : galmuri11_36_0_0_0","\n","^Controls_Battle_8 : galmuri11_36_0_0_0","\n","^Wait_InputBind : galmuri11_30_0_0_0","\n","^Detect_DuplicateBind : galmuri11_30_0_0_0","\n","^Mato_StatusIcon_Text : galmuri11_24_0_0_0","\n","^Mato_EquipIcon_Text : galmuri11_24_0_0_0","\n","^Mato_StatusTitle_Text : galmuri11_48_0_0_0","\n","^Mato_EquipTitle_Text : galmuri11_48_0_0_0","\n","^Mato_NextLevel_Text : galmuri11_24_0_0_0","\n","^Item_Description : galmuri11_24_-5_15_64","\n","^Item_Slot_Name : galmuri11_36_0_0_64","\n","^Super_Equip : galmuri11_24_0_0_0","\n","^Super_Details : galmuri11_24_0_0_0","\n","^Normal_Equip1 : galmuri11_24_0_0_0","\n","^Normal_Equip2 : galmuri11_24_0_0_0","\n","^Normal_Details : galmuri11_24_0_0_0","\n","^Load_Prompt : galmuri11_36_0_0_0","\n","^Load_Prompt_Yes : galmuri11_36_0_0_0","\n","^Load_Prompt_No : galmuri11_36_0_0_0","\n",["done",{"#f":5,"#n":"g-0"}],null],"done",{"#f":1}],"listDefs":{}}